binance_context_server/__init__.py
binance_context_server/binance_client.py
binance_context_server/resources.py
binance_context_server/server.py
binance_context_server/tools.py
binance_context_server-1.1.0.dist-info/METADATA
binance_context_server-1.1.0.dist-info/WHEEL
binance_context_server-1.1.0.dist-info/entry_points.txt
binance_context_server-1.1.0.dist-info/licenses/LICENSE
binance_context_server-1.1.0.dist-info/RECORD
