Metadata-Version: 2.4
Name: binance-context-server
Version: 1.1.0
Summary: Binance MCP Server for cryptocurrency market data and trading
Author-email: hocestnonsatis <hocestnonsatis@example.com>
License-File: LICENSE
Keywords: api,binance,cryptocurrency,market-data,mcp,trading
Classifier: Development Status :: 4 - Beta
Classifier: Intended Audience :: Developers
Classifier: License :: OSI Approved :: MIT License
Classifier: Operating System :: OS Independent
Classifier: Programming Language :: Python :: 3
Classifier: Programming Language :: Python :: 3.12
Classifier: Programming Language :: Python :: 3.13
Classifier: Topic :: Office/Business :: Financial
Classifier: Topic :: Software Development :: Libraries :: Python Modules
Requires-Python: >=3.12
Requires-Dist: anyio>=4.0.0
Requires-Dist: httpx>=0.27.0
Requires-Dist: mcp>=1.0.0
Requires-Dist: pandas-ta>=0.4.71b0
Requires-Dist: pydantic>=2.0.0
Requires-Dist: python-binance>=1.0.19
Provides-Extra: build
Requires-Dist: build>=0.10.0; extra == 'build'
Requires-Dist: twine>=4.0.0; extra == 'build'
Provides-Extra: dev
Requires-Dist: black>=23.0.0; extra == 'dev'
Requires-Dist: mypy>=1.5.0; extra == 'dev'
Requires-Dist: pytest-asyncio>=0.21.0; extra == 'dev'
Requires-Dist: pytest-cov>=4.0.0; extra == 'dev'
Requires-Dist: pytest>=7.0.0; extra == 'dev'
Requires-Dist: ruff>=0.1.0; extra == 'dev'
